sdial.py
sdial-0.1.0a2.dist-info/licenses/LICENSE
sdial-0.1.0a2.dist-info/METADATA
sdial-0.1.0a2.dist-info/WHEEL
sdial-0.1.0a2.dist-info/top_level.txt
sdial-0.1.0a2.dist-info/RECORD
