Metadata-Version: 2.4
Name: sdial
Version: 0.1.0a2
Summary: Speed dial for the CLI-phile.
Author-email: Jifeng Wu <jifengwu2k@gmail.com>
License-Expression: MIT
Project-URL: Homepage, https://github.com/jifengwu2k/sdial
Project-URL: Bug Tracker, https://github.com/jifengwu2k/sdial/issues
Classifier: Programming Language :: Python :: 2
Classifier: Programming Language :: Python :: 3
Classifier: Operating System :: OS Independent
Requires-Python: >=2
License-File: LICENSE
Requires-Dist: cowlist
Requires-Dist: ctypes-unicode-proclaunch
Requires-Dist: directory-file-mapping
Requires-Dist: get-unicode-multiline-input-with-editor
Requires-Dist: get-unicode-shell
Requires-Dist: sorted-fractionally-indexed-cowlist-set
Requires-Dist: textcompat
Dynamic: license-file
